{
  "week": 12,
  "season": 2025,
  "updated": "2025-11-23T04:17:41.775983",
  "source": "ESPN API",
  "games": [
    {
      "week": 12,
      "date": "2025-11-23T18:00Z",
      "home_team": "Chicago Bears",
      "away_team": "Pittsburgh Steelers",
      "home_score": null,
      "away_score": null,
      "status": "STATUS_SCHEDULED"
    },
    {
      "week": 12,
      "date": "2025-11-23T18:00Z",
      "home_team": "Cincinnati Bengals",
      "away_team": "New England Patriots",
      "home_score": null,
      "away_score": null,
      "status": "STATUS_SCHEDULED"
    },
    {
      "week": 12,
      "date": "2025-11-23T18:00Z",
      "home_team": "Detroit Lions",
      "away_team": "New York Giants",
      "home_score": null,
      "away_score": null,
      "status": "STATUS_SCHEDULED"
    },
    {
      "week": 12,
      "date": "2025-11-23T18:00Z",
      "home_team": "Green Bay Packers",
      "away_team": "Minnesota Vikings",
      "home_score": null,
      "away_score": null,
      "status": "STATUS_SCHEDULED"
    },
    {
      "week": 12,
      "date": "2025-11-23T18:00Z",
      "home_team": "Tennessee Titans",
      "away_team": "Seattle Seahawks",
      "home_score": null,
      "away_score": null,
      "status": "STATUS_SCHEDULED"
    },
    {
      "week": 12,
      "date": "2025-11-23T18:00Z",
      "home_team": "Kansas City Chiefs",
      "away_team": "Indianapolis Colts",
      "home_score": null,
      "away_score": null,
      "status": "STATUS_SCHEDULED"
    },
    {
      "week": 12,
      "date": "2025-11-23T18:00Z",
      "home_team": "Baltimore Ravens",
      "away_team": "New York Jets",
      "home_score": null,
      "away_score": null,
      "status": "STATUS_SCHEDULED"
    },
    {
      "week": 12,
      "date": "2025-11-23T21:05Z",
      "home_team": "Las Vegas Raiders",
      "away_team": "Cleveland Browns",
      "home_score": null,
      "away_score": null,
      "status": "STATUS_SCHEDULED"
    },
    {
      "week": 12,
      "date": "2025-11-23T21:05Z",
      "home_team": "Arizona Cardinals",
      "away_team": "Jacksonville Jaguars",
      "home_score": null,
      "away_score": null,
      "status": "STATUS_SCHEDULED"
    },
    {
      "week": 12,
      "date": "2025-11-23T21:25Z",
      "home_team": "Dallas Cowboys",
      "away_team": "Philadelphia Eagles",
      "home_score": null,
      "away_score": null,
      "status": "STATUS_SCHEDULED"
    },
    {
      "week": 12,
      "date": "2025-11-23T21:25Z",
      "home_team": "New Orleans Saints",
      "away_team": "Atlanta Falcons",
      "home_score": null,
      "away_score": null,
      "status": "STATUS_SCHEDULED"
    },
    {
      "week": 12,
      "date": "2025-11-24T01:20Z",
      "home_team": "Los Angeles Rams",
      "away_team": "Tampa Bay Buccaneers",
      "home_score": null,
      "away_score": null,
      "status": "STATUS_SCHEDULED"
    },
    {
      "week": 12,
      "date": "2025-11-21T01:15Z",
      "home_team": "Houston Texans",
      "away_team": "Buffalo Bills",
      "home_score": 23,
      "away_score": 19,
      "status": "STATUS_FINAL"
    },
    {
      "week": 12,
      "date": "2025-11-25T01:15Z",
      "home_team": "San Francisco 49ers",
      "away_team": "Carolina Panthers",
      "home_score": null,
      "away_score": null,
      "status": "STATUS_SCHEDULED"
    }
  ]
}